m269_25j_student/__init__.py
m269_25j_student/_version.py
m269_25j_student-0.1.1.data/data/share/jupyter/labextensions/m269-25j-student/package.json
m269_25j_student-0.1.1.data/data/share/jupyter/labextensions/m269-25j-student/static/509.d5d2f9bf8efe781aebd4.js
m269_25j_student-0.1.1.data/data/share/jupyter/labextensions/m269-25j-student/static/728.03cf7ba6fa962dc8e184.js
m269_25j_student-0.1.1.data/data/share/jupyter/labextensions/m269-25j-student/static/remoteEntry.8339f5fcf3d21fa93a06.js
m269_25j_student-0.1.1.data/data/share/jupyter/labextensions/m269-25j-student/static/style.js
m269_25j_student-0.1.1.data/data/share/jupyter/labextensions/m269-25j-student/static/third-party-licenses.json
m269_25j_student-0.1.1.data/data/share/jupyter/labextensions/m269-25j-student/install.json
m269_25j_student-0.1.1.dist-info/METADATA
m269_25j_student-0.1.1.dist-info/WHEEL
m269_25j_student-0.1.1.dist-info/licenses/LICENSE
m269_25j_student-0.1.1.dist-info/RECORD
