Metadata-Version: 2.1
Name: m269_25j_student
Version: 0.1.1
Summary: An extension for OU Students studying M269 in 25J
Project-URL: Homepage, https://github.com/dsa-ou/m269-25j-student
Project-URL: Bug Tracker, https://github.com/dsa-ou/m269-25j-student/issues
Project-URL: Repository, https://github.com/dsa-ou/m269-25j-student.git
Author-email: Oli Howson <oli.howson@open.ac.uk>
License: BSD 3-Clause License
License-File: LICENSE
Keywords: jupyter,jupyterlab,jupyterlab-extension
Classifier: Framework :: Jupyter
Classifier: Framework :: Jupyter :: JupyterLab
Classifier: Framework :: Jupyter :: JupyterLab :: 4
Classifier: Framework :: Jupyter :: JupyterLab :: Extensions
Classifier: Framework :: Jupyter :: JupyterLab :: Extensions :: Prebuilt
Classifier: License :: OSI Approved :: BSD License
Classifier: Programming Language :: Python
Classifier: Programming Language :: Python :: 3
Classifier: Programming Language :: Python :: 3.9
Classifier: Programming Language :: Python :: 3.10
Classifier: Programming Language :: Python :: 3.11
Classifier: Programming Language :: Python :: 3.12
Classifier: Programming Language :: Python :: 3.13
Requires-Python: >=3.9
